[
  {
    "id": "okgj5cq",
    "author": "Last_Cod_998",
    "body_html": "&lt;div class=\"md\"&gt;&lt;p&gt;&amp;quot;I can&amp;#39;t stand the term &amp;#39;empathy,&amp;#39; actually. I think &amp;#39;empathy&amp;#39; is a made up New Age word that does a lot of damage.&amp;quot; Charlie Kirk.&lt;/p&gt;\n\n&lt;p&gt;“You will never live in a society when you have an armed citizenry and you won&amp;#39;t have a single gun death. That is nonsense. It&amp;#39;s drivel. But I... think it&amp;#39;s worth to have a cost of, unfortunately, some gun deaths every single year so that we can have the Second Amendment to protect our other God-given rights. That is a prudent deal. It is rational.” Charlie Kirk&lt;/p&gt;\n\n&lt;p&gt;Kirk was speaking at a debate hosted by his nonprofit political organization. Immediately before the shooting, Kirk was taking questions for an audience member about mass shootings and gun violence.&lt;/p&gt;\n\n&lt;p&gt;“Do you know how many transgender Americans have been mass shooters over the last 10 years?” an audience member asked. Kirk responded, “Too many.”&lt;/p&gt;\n\n&lt;p&gt;The questioner followed up: “Do you know how many mass shooters there have been in America over the last 10 years?”&lt;/p&gt;\n\n&lt;p&gt;“Counting or not counting gang violence?” Kirk asked.&lt;/p&gt;\n\n&lt;p&gt;Then a single shot rang out.&lt;/p&gt;\n\n&lt;p&gt;Utah legislature (R) loosened gun laws on college campuses (May 2025) … Charlie Kirk shot dead on a Utah college campus (today)&lt;/p&gt;\n\n&lt;p&gt;University of Utah policy change allowing open carry on campus &lt;a href=\"https://attheu.utah.edu/facultystaff/new-rules-for-concealed-weapons-on-campus/\"&gt;https://attheu.utah.edu/facultystaff/new-rules-for-concealed-weapons-on-campus/&lt;/a&gt;&lt;/p&gt;\n\n&lt;p&gt;Utah State Legislature passed Republican-sponsored law &lt;a href=\"https://le.utah.gov/%7E2025/bills/static/HB0128.html\"&gt;https://le.utah.gov/~2025/bills/static/HB0128.html&lt;/a&gt;&lt;/p&gt;\n&lt;/div&gt;",
    "score": 41,
    "is_submitter": false,
    "created_utc": 1778166001,
    "distinguished": null,
    "parent_id": "t3_1t6cvxh",
    "permalink": "/r/FreedomofSpeech/comments/1t6cvxh/dont_let_the_toxic_rightwing_propaganda_machine/okgj5cq/",
    "replies": [
      {
        "id": "okgkv22",
        "author": "SpinningHead",
        "body_html": "&lt;div class=\"md\"&gt;&lt;p&gt;Sounds like a real POS.&lt;/p&gt;\n&lt;/div&gt;",
        "score": 27,
        "is_submitter": false,
        "created_utc": 1778166465,
        "distinguished": null,
        "parent_id": "t1_okgj5cq",
        "permalink": "/r/FreedomofSpeech/comments/1t6cvxh/dont_let_the_toxic_rightwing_propaganda_machine/okgkv22/",
        "replies": [
          {
            "id": "okgxdc6",
            "author": "TienSwitch",
            "body_html": "&lt;div class=\"md\"&gt;&lt;p&gt;He was. More than that, he was an animalistic, America-hating J6er who pushed the ultra pro-pedophile ideology of Christian Nationalism while dedicating himself to mastering being stupid to such a level that it actually defied the brain’s bottom level of cognitive capability.&lt;/p&gt;\n&lt;/div&gt;",
            "score": 19,
            "is_submitter": false,
            "created_utc": 1778169762,
            "distinguished": null,
            "parent_id": "t1_okgkv22",
            "permalink": "/r/FreedomofSpeech/comments/1t6cvxh/dont_let_the_toxic_rightwing_propaganda_machine/okgxdc6/",
            "replies": []
          },
          {
            "id": "okhzjn1",
            "author": "Zorkflerp",
            "body_html": "&lt;div class=\"md\"&gt;&lt;p&gt;I have a neighbor that spray painted “I AM CHARLIE KIRK!” in large face on his garage door. He may not understand that it isn&amp;#39;t a good thing to be.&lt;/p&gt;\n&lt;/div&gt;",
            "score": 2,
            "is_submitter": false,
            "created_utc": 1778179902,
            "distinguished": null,
            "parent_id": "t1_okgkv22",
            "permalink": "/r/FreedomofSpeech/comments/1t6cvxh/dont_let_the_toxic_rightwing_propaganda_machine/okhzjn1/",
            "replies": []
          },
          {
            "id": "okibzy7",
            "author": "GrinchWhoStoleEaster",
            "body_html": "&lt;div class=\"md\"&gt;&lt;p&gt;Sounds like a nazi.&lt;/p&gt;\n&lt;/div&gt;",
            "score": 2,
            "is_submitter": false,
            "created_utc": 1778183289,
            "distinguished": null,
            "parent_id": "t1_okgkv22",
            "permalink": "/r/FreedomofSpeech/comments/1t6cvxh/dont_let_the_toxic_rightwing_propaganda_machine/okibzy7/",
            "replies": []
          }
        ]
      },
      {
        "id": "oki1o26",
        "author": "Mr_Monday92",
        "body_html": "&lt;div class=\"md\"&gt;&lt;p&gt;You forgot the one where he said he feels unsafe in a plane flown by a black person &lt;/p&gt;\n&lt;/div&gt;",
        "score": 2,
        "is_submitter": false,
        "created_utc": 1778180464,
        "distinguished": null,
        "parent_id": "t1_okgj5cq",
        "permalink": "/r/FreedomofSpeech/comments/1t6cvxh/dont_let_the_toxic_rightwing_propaganda_machine/oki1o26/",
        "replies": []
      },
      {
        "id": "okiawx5",
        "author": "Waymore_Gibbs",
        "body_html": "&lt;div class=\"md\"&gt;&lt;p&gt;Charlie Kirk was incapable of empathy.&lt;/p&gt;\n&lt;/div&gt;",
        "score": 2,
        "is_submitter": false,
        "created_utc": 1778182989,
        "distinguished": null,
        "parent_id": "t1_okgj5cq",
        "permalink": "/r/FreedomofSpeech/comments/1t6cvxh/dont_let_the_toxic_rightwing_propaganda_machine/okiawx5/",
        "replies": []
      }
    ]
  },
  {
    "id": "okgp2gp",
    "author": "Erratic_-Prophet",
    "body_html": "&lt;div class=\"md\"&gt;&lt;p&gt;Dude was literally shot by a white man while blaming minorities for gun violence. He died the way he lived, being a lying bigot. &lt;/p&gt;\n&lt;/div&gt;",
    "score": 30,
    "is_submitter": false,
    "created_utc": 1778167591,
    "distinguished": null,
    "parent_id": "t3_1t6cvxh",
    "permalink": "/r/FreedomofSpeech/comments/1t6cvxh/dont_let_the_toxic_rightwing_propaganda_machine/okgp2gp/",
    "replies": []
  },
  {
    "id": "okgi8kk",
    "author": "[deleted]",
    "body_html": "&lt;div class=\"md\"&gt;&lt;p&gt;[removed]&lt;/p&gt;\n&lt;/div&gt;",
    "score": 75,
    "is_submitter": false,
    "created_utc": 1778165757,
    "distinguished": null,
    "parent_id": "t3_1t6cvxh",
    "permalink": "/r/FreedomofSpeech/comments/1t6cvxh/dont_let_the_toxic_rightwing_propaganda_machine/okgi8kk/",
    "replies": [
      {
        "id": "okgsl76",
        "author": "terragutti",
        "body_html": "&lt;div class=\"md\"&gt;&lt;p&gt;Totally agree with your sentiment, but also, he made a career out of it, and became super successful doing it. Kinda scary that someone like him can convince so many people. The conservative propaganda machine was really working hard back then with the so and so DESTROYS, blah blah blah OWNS, intellectual so and so WHATEVERS&lt;/p&gt;\n\n&lt;p&gt;And we still see the same media tactics today. &lt;/p&gt;\n&lt;/div&gt;",
        "score": 17,
        "is_submitter": false,
        "created_utc": 1778168519,
        "distinguished": null,
        "parent_id": "t1_okgi8kk",
        "permalink": "/r/FreedomofSpeech/comments/1t6cvxh/dont_let_the_toxic_rightwing_propaganda_machine/okgsl76/",
        "replies": [
          {
            "id": "okhrmtk",
            "author": "BigMikeXxxxX",
            "body_html": "&lt;div class=\"md\"&gt;&lt;p&gt;There&amp;#39;s also people on the left who do the exact same thing and I think in today&amp;#39;s world it&amp;#39;s necessary. There&amp;#39;s nothing wrong with allowing anyone and everyone to engage in open debate. Everyone deserves to have their opinions and views heard, but they should also be prepared to explain why they hold those ideologies too. &lt;/p&gt;\n&lt;/div&gt;",
            "score": 4,
            "is_submitter": false,
            "created_utc": 1778177745,
            "distinguished": null,
            "parent_id": "t1_okgsl76",
            "permalink": "/r/FreedomofSpeech/comments/1t6cvxh/dont_let_the_toxic_rightwing_propaganda_machine/okhrmtk/",
            "replies": []
          },
          {
            "id": "okhxllw",
            "author": "bobbymcpresscot",
            "body_html": "&lt;div class=\"md\"&gt;&lt;p&gt;Because there was some people that had a lot of snootiness. Liberals and their Prius’s or electric cars, or solar panels on their roof, talking about how they are saving the environment, and some guy was happy to sit there and point out that those people got scammed, they wasted time, effort, money, “but they never got me!”&lt;/p&gt;\n\n&lt;p&gt;People are willing to desperately latch onto things that comform\nTo their biases. There just happens to be a lot of disgruntled mediocre white men in a majority white country. &lt;/p&gt;\n&lt;/div&gt;",
            "score": 2,
            "is_submitter": false,
            "created_utc": 1778179376,
            "distinguished": null,
            "parent_id": "t1_okgsl76",
            "permalink": "/r/FreedomofSpeech/comments/1t6cvxh/dont_let_the_toxic_rightwing_propaganda_machine/okhxllw/",
            "replies": []
          },
          {
            "id": "okhynvg",
            "author": "EyeOughta",
            "body_html": "&lt;div class=\"md\"&gt;&lt;p&gt;Being a successful snake oil salesman is almost as old as prostitution. It&amp;#39;s not an accomplishment, it&amp;#39;s the natural end result of some grifters. &lt;/p&gt;\n&lt;/div&gt;",
            "score": 2,
            "is_submitter": false,
            "created_utc": 1778179665,
            "distinguished": null,
            "parent_id": "t1_okgsl76",
            "permalink": "/r/FreedomofSpeech/comments/1t6cvxh/dont_let_the_toxic_rightwing_propaganda_machine/okhynvg/",
            "replies": []
          },
          {
            "id": "oki6329",
            "author": "Spare_Layer_1069",
            "body_html": "&lt;div class=\"md\"&gt;&lt;p&gt;I&amp;#39;m so damn broke I almost want to grift money out of mediocre white dudes, so that way I can stop living paycheck to paycheck lol&lt;/p&gt;\n&lt;/div&gt;",
            "score": 2,
            "is_submitter": false,
            "created_utc": 1778181665,
            "distinguished": null,
            "parent_id": "t1_okgsl76",
            "permalink": "/r/FreedomofSpeech/comments/1t6cvxh/dont_let_the_toxic_rightwing_propaganda_machine/oki6329/",
            "replies": []
          },
          {
            "id": "oki75sm",
            "author": "frenchezz",
            "body_html": "&lt;div class=\"md\"&gt;&lt;p&gt;Lol that&amp;#39;s the daily beast headlines that get posted here ad naseum. &lt;/p&gt;\n&lt;/div&gt;",
            "score": 2,
            "is_submitter": false,
            "created_utc": 1778181959,
            "distinguished": null,
            "parent_id": "t1_okgsl76",
            "permalink": "/r/FreedomofSpeech/comments/1t6cvxh/dont_let_the_toxic_rightwing_propaganda_machine/oki75sm/",
            "replies": []
          },
          {
            "id": "oki8b8f",
            "author": "Due_Night414",
            "body_html": "&lt;div class=\"md\"&gt;&lt;p&gt;The man made money off of his ego.  Big ego is associated with low tolerance for criticism.  Check.  Needs validation.  Check.  Lack of empathy.  Check.  Control issues.  Check.  Jealousy and resentment.  Check and check.  When you mix high ego with charisma without a conscience , though?  &lt;/p&gt;\n\n&lt;p&gt;He monetized this.  Someone else with the same psychological and emotional issues turned it into a presidency.  &lt;/p&gt;\n&lt;/div&gt;",
            "score": 2,
            "is_submitter": false,
            "created_utc": 1778182276,
            "distinguished": null,
            "parent_id": "t1_okgsl76",
            "permalink": "/r/FreedomofSpeech/comments/1t6cvxh/dont_let_the_toxic_rightwing_propaganda_machine/oki8b8f/",
            "replies": []
          },
          {
            "id": "okj1q5l",
            "author": "AggressiveBench9977",
            "body_html": "&lt;div class=\"md\"&gt;&lt;p&gt;Thats ignoring some huge context.&lt;/p&gt;\n\n&lt;p&gt;He didnt make a career out of it, he got funded by peter t and his gang. &lt;/p&gt;\n\n&lt;p&gt;Kirk would have been a nobody on his own if he didnt get a massive push from the right wing media to establish him. His greatest accomplishment was being a ignorant white male. &lt;/p&gt;\n&lt;/div&gt;",
            "score": 2,
            "is_submitter": false,
            "created_utc": 1778190518,
            "distinguished": null,
            "parent_id": "t1_okgsl76",
            "permalink": "/r/FreedomofSpeech/comments/1t6cvxh/dont_let_the_toxic_rightwing_propaganda_machine/okj1q5l/",
            "replies": []
          },
          {
            "id": "okgt7qe",
            "author": "crozinator33",
            "body_html": "&lt;div class=\"md\"&gt;&lt;p&gt;Back then?  &lt;/p&gt;\n&lt;/div&gt;",
            "score": 5,
            "is_submitter": false,
            "created_utc": 1778168681,
            "distinguished": null,
            "parent_id": "t1_okgsl76",
            "permalink": "/r/FreedomofSpeech/comments/1t6cvxh/dont_let_the_toxic_rightwing_propaganda_machine/okgt7qe/",
            "replies": []
          },
          {
            "id": "okhecm3",
            "author": "qwythebroken",
            "body_html": "&lt;div class=\"md\"&gt;&lt;p&gt;Beyond his general racist misogyny, he really inspired people with his words. Think of all his quotes his followers have been holding up to memorialize him, like; &amp;quot;...&amp;quot;, and &amp;quot;...&amp;quot;. &lt;/p&gt;\n\n&lt;p&gt;I mean, WOW! What a relatable message. Truly a profound man, with a once in a century mind that will undoubtedly inspire future generations throughout this millennia. &lt;/p&gt;\n\n&lt;p&gt;...you know, beyond the generic crayon eating racist misogyny. &lt;/p&gt;\n&lt;/div&gt;",
            "score": 2,
            "is_submitter": false,
            "created_utc": 1778174248,
            "distinguished": null,
            "parent_id": "t1_okgsl76",
            "permalink": "/r/FreedomofSpeech/comments/1t6cvxh/dont_let_the_toxic_rightwing_propaganda_machine/okhecm3/",
            "replies": []
          }
        ]
      },
      {
        "id": "okhkmbi",
        "author": "Available_Leather_10",
        "body_html": "&lt;div class=\"md\"&gt;&lt;p&gt;Nah, he totally had the look of a creepy sniffer dude. &lt;/p&gt;\n\n&lt;p&gt;And Erika was, is, and will be an astounding mediocrity, level-setting his target for creepy sniffing.&lt;/p&gt;\n&lt;/div&gt;",
        "score": 2,
        "is_submitter": false,
        "created_utc": 1778175886,
        "distinguished": null,
        "parent_id": "t1_okgi8kk",
        "permalink": "/r/FreedomofSpeech/comments/1t6cvxh/dont_let_the_toxic_rightwing_propaganda_machine/okhkmbi/",
        "replies": []
      }
    ]
  },
  {
    "id": "okgmfsm",
    "author": "Suitable_Community66",
    "body_html": "&lt;div class=\"md\"&gt;&lt;p&gt;He was also vehemently transphobic and his promotion of his hate towards our community was severely damaging to our quest for equality &lt;/p&gt;\n&lt;/div&gt;",
    "score": 19,
    "is_submitter": false,
    "created_utc": 1778166890,
    "distinguished": null,
    "parent_id": "t3_1t6cvxh",
    "permalink": "/r/FreedomofSpeech/comments/1t6cvxh/dont_let_the_toxic_rightwing_propaganda_machine/okgmfsm/",
    "replies": []
  },
  {
    "id": "okgnk0k",
    "author": "Mroopsimexciting",
    "body_html": "&lt;div class=\"md\"&gt;&lt;p&gt;Fuck Charlie Kirk &lt;/p&gt;\n&lt;/div&gt;",
    "score": 10,
    "is_submitter": false,
    "created_utc": 1778167189,
    "distinguished": null,
    "parent_id": "t3_1t6cvxh",
    "permalink": "/r/FreedomofSpeech/comments/1t6cvxh/dont_let_the_toxic_rightwing_propaganda_machine/okgnk0k/",
    "replies": [
      {
        "id": "okhl2g5",
        "author": "01SeaChange01",
        "body_html": "&lt;div class=\"md\"&gt;&lt;p&gt;But really, fuck that fucking POS.&lt;/p&gt;\n&lt;/div&gt;",
        "score": 3,
        "is_submitter": false,
        "created_utc": 1778176003,
        "distinguished": null,
        "parent_id": "t1_okgnk0k",
        "permalink": "/r/FreedomofSpeech/comments/1t6cvxh/dont_let_the_toxic_rightwing_propaganda_machine/okhl2g5/",
        "replies": []
      },
      {
        "id": "okjcn8v",
        "author": "Master_Maniac",
        "body_html": "&lt;div class=\"md\"&gt;&lt;p&gt;Erika, upon learning that her husband was violently mirdered:&lt;/p&gt;\n\n&lt;p&gt;&lt;a href=\"https://giphy.com/gifs/VIt0DX9mrsaARz0yWw\" target=\"_blank\"&gt;https://giphy.com/gifs/VIt0DX9mrsaARz0yWw&lt;/a&gt;&lt;/p&gt;\n&lt;/div&gt;",
        "score": 2,
        "is_submitter": false,
        "created_utc": 1778194006,
        "distinguished": null,
        "parent_id": "t1_okgnk0k",
        "permalink": "/r/FreedomofSpeech/comments/1t6cvxh/dont_let_the_toxic_rightwing_propaganda_machine/okjcn8v/",
        "replies": []
      }
    ]
  },
  {
    "id": "okgpvt5",
    "author": "The-Happy-Cow-Arts",
    "body_html": "&lt;div class=\"md\"&gt;&lt;p&gt;He was just a hateful man with bad takes. Lots of good people get killed all the time in evil ways by evil people. Read the epstein files. &lt;/p&gt;\n\n&lt;p&gt;Not shedding a tear for Charlie lol. &lt;/p&gt;\n&lt;/div&gt;",
    "score": 11,
    "is_submitter": false,
    "created_utc": 1778167807,
    "distinguished": null,
    "parent_id": "t3_1t6cvxh",
    "permalink": "/r/FreedomofSpeech/comments/1t6cvxh/dont_let_the_toxic_rightwing_propaganda_machine/okgpvt5/",
    "replies": []
  },
  {
    "id": "okhbqjc",
    "author": "stupidmcdummy",
    "body_html": "&lt;div class=\"md\"&gt;&lt;p&gt;Ah yes, the best way to combat what you perceive to be right wing propaganda is with left wing propaganda.&lt;/p&gt;\n\n&lt;p&gt;Mediocre?  He dropped out of college and started a movement.  Like it or hate it, that&amp;#39;s not mediocrity.&lt;/p&gt;\n\n&lt;p&gt;Charlie was an effective speaker and debater.  Like him or hate him, pretending he wasn&amp;#39;t is just silly.&lt;/p&gt;\n\n&lt;p&gt;He&amp;#39;s not a saint, but he didn&amp;#39;t deserve a bullet and he certainly doesn&amp;#39;t deserve the level of hatred people assume is acceptable.  You didn&amp;#39;t agree with him.  That&amp;#39;s not only fine, but I would defend your right to do so.&lt;/p&gt;\n\n&lt;p&gt;You don&amp;#39;t win a propaganda war with propaganda.  You win it with truth.  This nonsense isn&amp;#39;t remotely true.&lt;/p&gt;\n&lt;/div&gt;",
    "score": 4,
    "is_submitter": false,
    "created_utc": 1778173565,
    "distinguished": null,
    "parent_id": "t3_1t6cvxh",
    "permalink": "/r/FreedomofSpeech/comments/1t6cvxh/dont_let_the_toxic_rightwing_propaganda_machine/okhbqjc/",
    "replies": [
      {
        "id": "oki7uw1",
        "author": "Inglorious186",
        "body_html": "&lt;div class=\"md\"&gt;&lt;p&gt;Hard to argue that he was a successful debater when he would only agree to debate unprepared college kids with his preplanned responses. Whenever he ran across someone who knows that they were talking about it became quite clear that CK was only good at interrupting and talking over points that proved him wrong. &lt;/p&gt;\n&lt;/div&gt;",
        "score": 2,
        "is_submitter": false,
        "created_utc": 1778182151,
        "distinguished": null,
        "parent_id": "t1_okhbqjc",
        "permalink": "/r/FreedomofSpeech/comments/1t6cvxh/dont_let_the_toxic_rightwing_propaganda_machine/oki7uw1/",
        "replies": [
          {
            "id": "okibqe4",
            "author": "FourtyMichaelMichael",
            "body_html": "&lt;div class=\"md\"&gt;&lt;p&gt;Moron college kids could not refuse an open mic... And you hated him because held up a mirror.&lt;/p&gt;\n\n&lt;p&gt;Be honest.&lt;/p&gt;\n&lt;/div&gt;",
            "score": 2,
            "is_submitter": false,
            "created_utc": 1778183216,
            "distinguished": null,
            "parent_id": "t1_oki7uw1",
            "permalink": "/r/FreedomofSpeech/comments/1t6cvxh/dont_let_the_toxic_rightwing_propaganda_machine/okibqe4/",
            "replies": []
          }
        ]
      }
    ]
  },
  {
    "id": "okghycd",
    "author": "[deleted]",
    "body_html": "&lt;div class=\"md\"&gt;&lt;p&gt;[removed]&lt;/p&gt;\n&lt;/div&gt;",
    "score": 14,
    "is_submitter": false,
    "created_utc": 1778165680,
    "distinguished": null,
    "parent_id": "t3_1t6cvxh",
    "permalink": "/r/FreedomofSpeech/comments/1t6cvxh/dont_let_the_toxic_rightwing_propaganda_machine/okghycd/",
    "replies": []
  },
  {
    "id": "okhhsps",
    "author": "MamaRunsThis",
    "body_html": "&lt;div class=\"md\"&gt;&lt;p&gt;Whatever gets you bottom feeders through the day I guess&lt;/p&gt;\n&lt;/div&gt;",
    "score": 3,
    "is_submitter": false,
    "created_utc": 1778175146,
    "distinguished": null,
    "parent_id": "t3_1t6cvxh",
    "permalink": "/r/FreedomofSpeech/comments/1t6cvxh/dont_let_the_toxic_rightwing_propaganda_machine/okhhsps/",
    "replies": [
      {
        "id": "okild8q",
        "author": "GO_BIRDS150",
        "body_html": "&lt;div class=\"md\"&gt;&lt;p&gt;This place is a cess pool lol&lt;/p&gt;\n&lt;/div&gt;",
        "score": 2,
        "is_submitter": false,
        "created_utc": 1778185870,
        "distinguished": null,
        "parent_id": "t1_okhhsps",
        "permalink": "/r/FreedomofSpeech/comments/1t6cvxh/dont_let_the_toxic_rightwing_propaganda_machine/okild8q/",
        "replies": []
      }
    ]
  },
  {
    "id": "okgoawi",
    "author": "anrwlias",
    "body_html": "&lt;div class=\"md\"&gt;&lt;p&gt;Whenever I see someone trying to claim that Kirk was a great man, I always ask for examples of his wisdom. &lt;/p&gt;\n\n&lt;p&gt;I never get any. &lt;/p&gt;\n&lt;/div&gt;",
    "score": 8,
    "is_submitter": false,
    "created_utc": 1778167388,
    "distinguished": null,
    "parent_id": "t3_1t6cvxh",
    "permalink": "/r/FreedomofSpeech/comments/1t6cvxh/dont_let_the_toxic_rightwing_propaganda_machine/okgoawi/",
    "replies": []
  },
  {
    "id": "okgqu99",
    "author": "Spiritual_Egg_700",
    "body_html": "&lt;div class=\"md\"&gt;&lt;p&gt;Very well put. Kudo&amp;#39;s.&lt;/p&gt;\n&lt;/div&gt;",
    "score": 5,
    "is_submitter": false,
    "created_utc": 1778168060,
    "distinguished": null,
    "parent_id": "t3_1t6cvxh",
    "permalink": "/r/FreedomofSpeech/comments/1t6cvxh/dont_let_the_toxic_rightwing_propaganda_machine/okgqu99/",
    "replies": []
  },
  {
    "id": "okgtz1v",
    "author": "Subject-Ad-7530",
    "body_html": "&lt;div class=\"md\"&gt;&lt;p&gt;Wrong, his legacy is the face swap meme and his weird wife.&lt;/p&gt;\n&lt;/div&gt;",
    "score": 5,
    "is_submitter": false,
    "created_utc": 1778168876,
    "distinguished": null,
    "parent_id": "t3_1t6cvxh",
    "permalink": "/r/FreedomofSpeech/comments/1t6cvxh/dont_let_the_toxic_rightwing_propaganda_machine/okgtz1v/",
    "replies": []
  },
  {
    "id": "okgu0hn",
    "author": "TienSwitch",
    "body_html": "&lt;div class=\"md\"&gt;&lt;p&gt;In a totally normal world, Charlie Kirk would never have been murdered for speaking to college kids.&lt;/p&gt;\n\n&lt;p&gt;That’s because in a totally normal world, the only thing Charlie Kirk would have been saying to college kids is, “Would you like fries with that?”.&lt;/p&gt;\n&lt;/div&gt;",
    "score": 6,
    "is_submitter": false,
    "created_utc": 1778168886,
    "distinguished": null,
    "parent_id": "t3_1t6cvxh",
    "permalink": "/r/FreedomofSpeech/comments/1t6cvxh/dont_let_the_toxic_rightwing_propaganda_machine/okgu0hn/",
    "replies": [
      {
        "id": "okgzjxk",
        "author": "SweetPrism",
        "body_html": "&lt;div class=\"md\"&gt;&lt;p&gt;He followed the cult playbook: 1. Realize that you are not going to accomplish your dream (getting into West Point), and know deep down you are not extraordinary in any meaningful way, but you believe you are still &amp;quot;destined for great things.&amp;quot; (Hitler, L. Ron Hubbard, Jim Jones, Rock Theriault, Rasputin...need I continue? I do credit him for having the ability to seize on the luck versus opportunity thing, though. He saw an opening and he took it).&lt;/p&gt;\n\n&lt;ol&gt;\n&lt;li&gt;&lt;p&gt;Preach to other mediocre white people that their economy is shit and they also aren&amp;#39;t accomplishing their dream for the same reasons (minorities). Everyone loves to blame someone else for their failures.&lt;/p&gt;&lt;/li&gt;\n&lt;li&gt;&lt;p&gt;Get in on the faster-moving grift (Remember when that Indian scammer said it was too hard to make money as a Democratic influencer because Democrats aren&amp;#39;t as easily fooled? Yeah. That). Cheat code: Merch. Republicans LOVE their merch.&lt;/p&gt;&lt;/li&gt;\n&lt;li&gt;&lt;p&gt;Find someone just as talentless as an accessory who has tried to get famous in every way possible because they are also mediocre (dating shows, pageants, Dead Hubby Grift Tour &amp;#39;26...).&lt;/p&gt;&lt;/li&gt;\n&lt;/ol&gt;\n&lt;/div&gt;",
        "score": 3,
        "is_submitter": false,
        "created_utc": 1778170342,
        "distinguished": null,
        "parent_id": "t1_okgu0hn",
        "permalink": "/r/FreedomofSpeech/comments/1t6cvxh/dont_let_the_toxic_rightwing_propaganda_machine/okgzjxk/",
        "replies": []
      }
    ]
  },
  {
    "id": "okgmdtq",
    "author": "Vivid_Witness8204",
    "body_html": "&lt;div class=\"md\"&gt;&lt;p&gt;He was just another two bit grifter.  &lt;/p&gt;\n&lt;/div&gt;",
    "score": 7,
    "is_submitter": false,
    "created_utc": 1778166875,
    "distinguished": null,
    "parent_id": "t3_1t6cvxh",
    "permalink": "/r/FreedomofSpeech/comments/1t6cvxh/dont_let_the_toxic_rightwing_propaganda_machine/okgmdtq/",
    "replies": []
  },
  {
    "id": "okgkoh8",
    "author": "Mysterious-Lab-5918",
    "body_html": "&lt;div class=\"md\"&gt;&lt;p&gt;The puppet has been silenced, yet the show continues...&lt;/p&gt;\n&lt;/div&gt;",
    "score": 6,
    "is_submitter": false,
    "created_utc": 1778166417,
    "distinguished": null,
    "parent_id": "t3_1t6cvxh",
    "permalink": "/r/FreedomofSpeech/comments/1t6cvxh/dont_let_the_toxic_rightwing_propaganda_machine/okgkoh8/",
    "replies": [
      {
        "id": "okj37xp",
        "author": "kick_start_cicada",
        "body_html": "&lt;div class=\"md\"&gt;&lt;p&gt;Very lyrical.  I likes it.&lt;/p&gt;\n&lt;/div&gt;",
        "score": 2,
        "is_submitter": false,
        "created_utc": 1778190971,
        "distinguished": null,
        "parent_id": "t1_okgkoh8",
        "permalink": "/r/FreedomofSpeech/comments/1t6cvxh/dont_let_the_toxic_rightwing_propaganda_machine/okj37xp/",
        "replies": []
      }
    ]
  },
  {
    "id": "okgq60h",
    "author": "[deleted]",
    "body_html": "&lt;div class=\"md\"&gt;&lt;p&gt;[deleted]&lt;/p&gt;\n&lt;/div&gt;",
    "score": 7,
    "is_submitter": false,
    "created_utc": 1778167882,
    "distinguished": null,
    "parent_id": "t3_1t6cvxh",
    "permalink": "/r/FreedomofSpeech/comments/1t6cvxh/dont_let_the_toxic_rightwing_propaganda_machine/okgq60h/",
    "replies": [
      {
        "id": "oki978u",
        "author": "Tokyo-MontanaExpress",
        "body_html": "&lt;div class=\"md\"&gt;&lt;p&gt;And getting Democratic House speakers, VA nurses, and liberal white American mothers murdered. &lt;/p&gt;\n&lt;/div&gt;",
        "score": 2,
        "is_submitter": false,
        "created_utc": 1778182520,
        "distinguished": null,
        "parent_id": "t1_okgq60h",
        "permalink": "/r/FreedomofSpeech/comments/1t6cvxh/dont_let_the_toxic_rightwing_propaganda_machine/oki978u/",
        "replies": []
      }
    ]
  },
  {
    "id": "okgoo6g",
    "author": "AlwaysFinnishInsider",
    "body_html": "&lt;div class=\"md\"&gt;&lt;p&gt;Kirk was so useless even West Point turned him away. Dumb kid with an even dumber fan base. &lt;/p&gt;\n&lt;/div&gt;",
    "score": 4,
    "is_submitter": false,
    "created_utc": 1778167486,
    "distinguished": null,
    "parent_id": "t3_1t6cvxh",
    "permalink": "/r/FreedomofSpeech/comments/1t6cvxh/dont_let_the_toxic_rightwing_propaganda_machine/okgoo6g/",
    "replies": [
      {
        "id": "okhhzqs",
        "author": "cameron8988",
        "body_html": "&lt;div class=\"md\"&gt;&lt;p&gt;west point is highly selective, it&amp;#39;s no surprise he didn&amp;#39;t get in. of course he dined out for years on the completely fabricated (and racist) assumption that his spot was given to a black woman. no honey. you were denied because you&amp;#39;re subpar.&lt;/p&gt;\n&lt;/div&gt;",
        "score": 3,
        "is_submitter": false,
        "created_utc": 1778175197,
        "distinguished": null,
        "parent_id": "t1_okgoo6g",
        "permalink": "/r/FreedomofSpeech/comments/1t6cvxh/dont_let_the_toxic_rightwing_propaganda_machine/okhhzqs/",
        "replies": []
      }
    ]
  },
  {
    "id": "okgquds",
    "author": "Xwp_lp",
    "body_html": "&lt;div class=\"md\"&gt;&lt;p&gt;He was the equivalent of a radical, right wing talk radio host. He just did his schtick in venues that included universities. But his listeners skewed 55 plus and white.&lt;/p&gt;\n&lt;/div&gt;",
    "score": 6,
    "is_submitter": false,
    "created_utc": 1778168061,
    "distinguished": null,
    "parent_id": "t3_1t6cvxh",
    "permalink": "/r/FreedomofSpeech/comments/1t6cvxh/dont_let_the_toxic_rightwing_propaganda_machine/okgquds/",
    "replies": []
  },
  {
    "id": "okgt5nh",
    "author": "Greedy-Employment917",
    "body_html": "&lt;div class=\"md\"&gt;&lt;p&gt;One day old reddit account. This is the first post.\nYou guys are being played by bots. &lt;/p&gt;\n&lt;/div&gt;",
    "score": 2,
    "is_submitter": false,
    "created_utc": 1778168666,
    "distinguished": null,
    "parent_id": "t3_1t6cvxh",
    "permalink": "/r/FreedomofSpeech/comments/1t6cvxh/dont_let_the_toxic_rightwing_propaganda_machine/okgt5nh/",
    "replies": [
      {
        "id": "okh4lvh",
        "author": "Updated_Autopsy",
        "body_html": "&lt;div class=\"md\"&gt;&lt;p&gt;I wouldn’t be surprised if some of the accounts responding are also bots.&lt;/p&gt;\n&lt;/div&gt;",
        "score": 3,
        "is_submitter": false,
        "created_utc": 1778171687,
        "distinguished": null,
        "parent_id": "t1_okgt5nh",
        "permalink": "/r/FreedomofSpeech/comments/1t6cvxh/dont_let_the_toxic_rightwing_propaganda_machine/okh4lvh/",
        "replies": []
      }
    ]
  },
  {
    "id": "okgw9zz",
    "author": "AllNamesTaken56",
    "body_html": "&lt;div class=\"md\"&gt;&lt;p&gt;Lol, so the Left once again approves of murder to further their sadistic hateful agenda!&lt;/p&gt;\n&lt;/div&gt;",
    "score": 2,
    "is_submitter": false,
    "created_utc": 1778169474,
    "distinguished": null,
    "parent_id": "t3_1t6cvxh",
    "permalink": "/r/FreedomofSpeech/comments/1t6cvxh/dont_let_the_toxic_rightwing_propaganda_machine/okgw9zz/",
    "replies": []
  },
  {
    "id": "okgwp3r",
    "author": "middle1984",
    "body_html": "&lt;div class=\"md\"&gt;&lt;p&gt;Yea getting a job on merit not sex or race who would stand for such a thing?&lt;/p&gt;\n&lt;/div&gt;",
    "score": 2,
    "is_submitter": false,
    "created_utc": 1778169584,
    "distinguished": null,
    "parent_id": "t3_1t6cvxh",
    "permalink": "/r/FreedomofSpeech/comments/1t6cvxh/dont_let_the_toxic_rightwing_propaganda_machine/okgwp3r/",
    "replies": []
  },
  {
    "id": "okgy1ca",
    "author": "VisibleElk9770",
    "body_html": "&lt;div class=\"md\"&gt;&lt;p&gt;An anti free speech leftist assassinates a man trying to have conversations and here you are cheering on the assassin in a free speech forum. Fucking ironic &lt;/p&gt;\n&lt;/div&gt;",
    "score": 2,
    "is_submitter": false,
    "created_utc": 1778169941,
    "distinguished": null,
    "parent_id": "t3_1t6cvxh",
    "permalink": "/r/FreedomofSpeech/comments/1t6cvxh/dont_let_the_toxic_rightwing_propaganda_machine/okgy1ca/",
    "replies": []
  },
  {
    "id": "okh04m9",
    "author": "Prestigious_Coffee28",
    "body_html": "&lt;div class=\"md\"&gt;&lt;p&gt;I don’t understand how the average redditor can’t wrap their head around what he said and instead just cry racism. I don’t know if it’s pathetic or hilarious. &lt;/p&gt;\n&lt;/div&gt;",
    "score": 2,
    "is_submitter": false,
    "created_utc": 1778170495,
    "distinguished": null,
    "parent_id": "t3_1t6cvxh",
    "permalink": "/r/FreedomofSpeech/comments/1t6cvxh/dont_let_the_toxic_rightwing_propaganda_machine/okh04m9/",
    "replies": []
  },
  {
    "id": "okh78p6",
    "author": "GraphicRoach",
    "body_html": "&lt;div class=\"md\"&gt;&lt;p&gt;&amp;quot;I’m glad he’s dead. He can no longer hurt innocent people!&amp;quot;&lt;/p&gt;\n\n&lt;p&gt;-President Donald Trump&lt;/p&gt;\n&lt;/div&gt;",
    "score": 2,
    "is_submitter": false,
    "created_utc": 1778172390,
    "distinguished": null,
    "parent_id": "t3_1t6cvxh",
    "permalink": "/r/FreedomofSpeech/comments/1t6cvxh/dont_let_the_toxic_rightwing_propaganda_machine/okh78p6/",
    "replies": []
  },
  {
    "id": "okh7qyx",
    "author": "LettuceTryOnceMore",
    "body_html": "&lt;div class=\"md\"&gt;&lt;p&gt;Is this another one of those lame Karma/Bait farm subreddits?&lt;/p&gt;\n\n&lt;p&gt;Not sure where rock bottom is but this app is plummeting towards it lol&lt;/p&gt;\n&lt;/div&gt;",
    "score": 2,
    "is_submitter": false,
    "created_utc": 1778172522,
    "distinguished": null,
    "parent_id": "t3_1t6cvxh",
    "permalink": "/r/FreedomofSpeech/comments/1t6cvxh/dont_let_the_toxic_rightwing_propaganda_machine/okh7qyx/",
    "replies": []
  },
  {
    "id": "okh7wmz",
    "author": "Mythic-Fairy",
    "body_html": "&lt;div class=\"md\"&gt;&lt;p&gt;Funny when the left turned a violent career criminal into one. Don&amp;#39;t be a hypocrite. &lt;/p&gt;\n\n&lt;p&gt;I wish both sides would sober up. &lt;/p&gt;\n&lt;/div&gt;",
    "score": 2,
    "is_submitter": false,
    "created_utc": 1778172564,
    "distinguished": null,
    "parent_id": "t3_1t6cvxh",
    "permalink": "/r/FreedomofSpeech/comments/1t6cvxh/dont_let_the_toxic_rightwing_propaganda_machine/okh7wmz/",
    "replies": []
  },
  {
    "id": "okhc8vv",
    "author": "Reasonable-Lack-9461",
    "body_html": "&lt;div class=\"md\"&gt;&lt;p&gt;Poor taste. I know where it feels like the hate is coming from, and it&amp;#39;s not Charlie.&lt;/p&gt;\n&lt;/div&gt;",
    "score": 2,
    "is_submitter": false,
    "created_utc": 1778173699,
    "distinguished": null,
    "parent_id": "t3_1t6cvxh",
    "permalink": "/r/FreedomofSpeech/comments/1t6cvxh/dont_let_the_toxic_rightwing_propaganda_machine/okhc8vv/",
    "replies": [
      {
        "id": "okhcme0",
        "author": "bunchout",
        "body_html": "&lt;div class=\"md\"&gt;&lt;p&gt;I mean, not anymore…&lt;/p&gt;\n&lt;/div&gt;",
        "score": 2,
        "is_submitter": false,
        "created_utc": 1778173797,
        "distinguished": null,
        "parent_id": "t1_okhc8vv",
        "permalink": "/r/FreedomofSpeech/comments/1t6cvxh/dont_let_the_toxic_rightwing_propaganda_machine/okhcme0/",
        "replies": []
      }
    ]
  },
  {
    "id": "okhd1tw",
    "author": "Mithrachs",
    "body_html": "&lt;div class=\"md\"&gt;&lt;p&gt;It’s poor taste to speak ill of the dead. These comments are disheartening &lt;/p&gt;\n&lt;/div&gt;",
    "score": 2,
    "is_submitter": false,
    "created_utc": 1778173910,
    "distinguished": null,
    "parent_id": "t3_1t6cvxh",
    "permalink": "/r/FreedomofSpeech/comments/1t6cvxh/dont_let_the_toxic_rightwing_propaganda_machine/okhd1tw/",
    "replies": []
  },
  {
    "id": "okhdbie",
    "author": "perfed-metal",
    "body_html": "&lt;div class=\"md\"&gt;&lt;p&gt;God you people need to stop demonizing people who disagree with you. He was not hateful he did drop out of college and then built the biggest public action group on the right and mobilized millions of people to vote. If he was left you be celebrating and I’m left slight left of center and I can see that. Stop with the crazy ass far left shit that got us democrats to lose the freaking election and probably this one coming up as well. People just don’t want crazy and Kirk views weee normal conservative views so stop demonizing people who disagree with you.&lt;/p&gt;\n&lt;/div&gt;",
    "score": 2,
    "is_submitter": false,
    "created_utc": 1778173980,
    "distinguished": null,
    "parent_id": "t3_1t6cvxh",
    "permalink": "/r/FreedomofSpeech/comments/1t6cvxh/dont_let_the_toxic_rightwing_propaganda_machine/okhdbie/",
    "replies": []
  },
  {
    "id": "okhhnla",
    "author": "Monk-Prior",
    "body_html": "&lt;div class=\"md\"&gt;&lt;p&gt;Don’t let your hatred for right-wingers justify murdering someone you don’t like in broad daylight.&lt;/p&gt;\n&lt;/div&gt;",
    "score": 2,
    "is_submitter": false,
    "created_utc": 1778175110,
    "distinguished": null,
    "parent_id": "t3_1t6cvxh",
    "permalink": "/r/FreedomofSpeech/comments/1t6cvxh/dont_let_the_toxic_rightwing_propaganda_machine/okhhnla/",
    "replies": []
  }
]